alphacast/__init__.py
alphacast/alphacast.py
alphacast-0.1.8.7.dist-info/licenses/LICENSE
alphacast-0.1.8.7.dist-info/METADATA
alphacast-0.1.8.7.dist-info/WHEEL
alphacast-0.1.8.7.dist-info/top_level.txt
alphacast-0.1.8.7.dist-info/RECORD
